Metadata-Version: 2.1
Name: not-so-badass
Version: 0.7
Summary: (not so) bad assessments
Home-page: https://github.com/fpom/badass
Author: Franck Pommereau
Author-email: franck.pommereau@univ-evry.fr
License: UNKNOWN
Platform: UNKNOWN
Classifier: Development Status :: 4 - Beta
Classifier: Intended Audience :: Education
Classifier: Topic :: Education
Classifier: License :: OSI Approved :: GNU General Public License (GPL)
Classifier: Programming Language :: Python :: 3.7
Classifier: Operating System :: OS Independent
Requires-Python: >=3.7
